[
    {
        "timestamp": "2025-06-25 18:41:58",
        "count": 1
    },
    {
        "timestamp": "2025-06-25 18:42:08",
        "count": 2
    },
    {
        "timestamp": "2025-06-25 18:42:18",
        "count": 3
    },
    {
        "timestamp": "2025-06-25 18:42:28",
        "count": 2
    },
    {
        "timestamp": "2025-06-25 18:42:48",
        "count": 3
    },
    {
        "timestamp": "2025-06-25 18:42:58",
        "count": 2
    },
    {
        "timestamp": "2025-06-25 18:43:08",
        "count": 3
    },
    {
        "timestamp": "2025-06-25 18:43:18",
        "count": 4
    },
    {
        "timestamp": "2025-06-25 18:43:38",
        "count": 3
    },
    {
        "timestamp": "2025-06-25 18:43:48",
        "count": 4
    },
    {
        "timestamp": "2025-06-25 18:43:58",
        "count": 3
    },
    {
        "timestamp": "2025-06-25 18:44:08",
        "count": 2
    },
    {
        "timestamp": "2025-06-25 18:44:18",
        "count": 3
    },
    {
        "timestamp": "2025-06-25 18:44:38",
        "count": 2
    },
    {
        "timestamp": "2025-06-25 18:44:48",
        "count": 1
    },
    {
        "timestamp": "2025-06-25 18:44:58",
        "count": 2
    },
    {
        "timestamp": "2025-06-25 18:45:08",
        "count": 1
    },
    {
        "timestamp": "2025-06-25 18:45:18",
        "count": 0
    },
    {
        "timestamp": "2025-06-25 18:45:28",
        "count": 1
    },
    {
        "timestamp": "2025-06-25 18:45:38",
        "count": 0
    },
    {
        "timestamp": "2025-06-25 18:47:38",
        "count": 1
    },
    {
        "timestamp": "2025-06-25 18:48:48",
        "count": 2
    },
    {
        "timestamp": "2025-06-25 18:49:08",
        "count": 1
    },
    {
        "timestamp": "2025-06-25 18:49:18",
        "count": 2
    },
    {
        "timestamp": "2025-06-25 18:49:28",
        "count": 3
    },
    {
        "timestamp": "2025-06-25 18:49:48",
        "count": 4
    },
    {
        "timestamp": "2025-06-25 18:49:58",
        "count": 3
    },
    {
        "timestamp": "2025-06-25 18:50:08",
        "count": 2
    },
    {
        "timestamp": "2025-06-25 18:50:18",
        "count": 3
    },
    {
        "timestamp": "2025-06-25 18:50:38",
        "count": 2
    },
    {
        "timestamp": "2025-06-25 18:50:48",
        "count": 3
    },
    {
        "timestamp": "2025-06-25 18:50:58",
        "count": 4
    },
    {
        "timestamp": "2025-06-25 18:51:08",
        "count": 3
    },
    {
        "timestamp": "2025-06-25 18:51:48",
        "count": 2
    },
    {
        "timestamp": "2025-06-25 18:51:58",
        "count": 1
    },
    {
        "timestamp": "2025-06-25 18:52:08",
        "count": 2
    },
    {
        "timestamp": "2025-06-25 18:52:18",
        "count": 1
    },
    {
        "timestamp": "2025-06-25 18:52:48",
        "count": 0
    },
    {
        "timestamp": "2025-06-25 18:53:08",
        "count": 1
    },
    {
        "timestamp": "2025-06-25 18:53:18",
        "count": 2
    },
    {
        "timestamp": "2025-06-25 18:53:28",
        "count": 3
    },
    {
        "timestamp": "2025-06-25 18:53:48",
        "count": 2
    },
    {
        "timestamp": "2025-06-25 18:54:08",
        "count": 3
    },
    {
        "timestamp": "2025-06-25 18:54:18",
        "count": 2
    },
    {
        "timestamp": "2025-06-25 18:54:28",
        "count": 1
    },
    {
        "timestamp": "2025-06-25 18:54:38",
        "count": 2
    },
    {
        "timestamp": "2025-06-25 18:54:48",
        "count": 1
    },
    {
        "timestamp": "2025-06-25 18:54:58",
        "count": 2
    },
    {
        "timestamp": "2025-06-25 18:55:08",
        "count": 3
    },
    {
        "timestamp": "2025-06-25 18:55:18",
        "count": 2
    },
    {
        "timestamp": "2025-06-25 18:55:28",
        "count": 3
    },
    {
        "timestamp": "2025-06-25 18:55:38",
        "count": 4
    },
    {
        "timestamp": "2025-06-25 18:55:48",
        "count": 5
    },
    {
        "timestamp": "2025-06-25 18:55:58",
        "count": 4
    },
    {
        "timestamp": "2025-06-25 18:56:08",
        "count": 3
    },
    {
        "timestamp": "2025-06-25 18:56:28",
        "count": 4
    },
    {
        "timestamp": "2025-06-25 18:56:38",
        "count": 3
    },
    {
        "timestamp": "2025-06-25 18:56:48",
        "count": 4
    },
    {
        "timestamp": "2025-06-25 18:56:58",
        "count": 5
    },
    {
        "timestamp": "2025-06-25 18:57:18",
        "count": 4
    },
    {
        "timestamp": "2025-06-25 18:57:28",
        "count": 5
    },
    {
        "timestamp": "2025-06-25 18:57:48",
        "count": 6
    },
    {
        "timestamp": "2025-06-25 18:58:18",
        "count": 7
    },
    {
        "timestamp": "2025-06-25 18:58:48",
        "count": 6
    },
    {
        "timestamp": "2025-06-25 18:59:08",
        "count": 5
    },
    {
        "timestamp": "2025-06-25 18:59:18",
        "count": 6
    },
    {
        "timestamp": "2025-06-25 18:59:28",
        "count": 5
    },
    {
        "timestamp": "2025-06-25 18:59:38",
        "count": 6
    },
    {
        "timestamp": "2025-06-25 19:00:08",
        "count": 5
    },
    {
        "timestamp": "2025-06-25 19:00:18",
        "count": 4
    },
    {
        "timestamp": "2025-06-25 19:00:28",
        "count": 3
    },
    {
        "timestamp": "2025-06-25 19:00:38",
        "count": 4
    },
    {
        "timestamp": "2025-06-25 19:00:48",
        "count": 5
    },
    {
        "timestamp": "2025-06-25 19:01:18",
        "count": 4
    },
    {
        "timestamp": "2025-06-25 19:01:28",
        "count": 5
    },
    {
        "timestamp": "2025-06-25 19:01:38",
        "count": 6
    },
    {
        "timestamp": "2025-06-25 19:02:18",
        "count": 7
    },
    {
        "timestamp": "2025-06-25 19:02:38",
        "count": 6
    },
    {
        "timestamp": "2025-06-25 19:02:58",
        "count": 7
    },
    {
        "timestamp": "2025-06-25 19:03:08",
        "count": 8
    },
    {
        "timestamp": "2025-06-25 19:03:18",
        "count": 7
    },
    {
        "timestamp": "2025-06-25 19:03:28",
        "count": 8
    },
    {
        "timestamp": "2025-06-25 19:03:38",
        "count": 7
    },
    {
        "timestamp": "2025-06-25 19:03:58",
        "count": 8
    },
    {
        "timestamp": "2025-06-25 19:04:08",
        "count": 9
    },
    {
        "timestamp": "2025-06-25 19:04:18",
        "count": 8
    },
    {
        "timestamp": "2025-06-25 19:04:28",
        "count": 9
    },
    {
        "timestamp": "2025-06-25 19:04:48",
        "count": 8
    },
    {
        "timestamp": "2025-06-25 19:04:58",
        "count": 7
    },
    {
        "timestamp": "2025-06-25 19:05:08",
        "count": 8
    },
    {
        "timestamp": "2025-06-25 19:05:18",
        "count": 9
    },
    {
        "timestamp": "2025-06-25 19:05:48",
        "count": 8
    },
    {
        "timestamp": "2025-06-25 19:06:18",
        "count": 7
    },
    {
        "timestamp": "2025-06-25 19:06:38",
        "count": 6
    },
    {
        "timestamp": "2025-06-25 19:07:08",
        "count": 7
    },
    {
        "timestamp": "2025-06-25 19:07:18",
        "count": 8
    },
    {
        "timestamp": "2025-06-25 19:07:48",
        "count": 7
    },
    {
        "timestamp": "2025-06-25 19:08:08",
        "count": 8
    },
    {
        "timestamp": "2025-06-25 19:08:38",
        "count": 9
    },
    {
        "timestamp": "2025-06-25 19:08:58",
        "count": 8
    },
    {
        "timestamp": "2025-06-25 19:09:08",
        "count": 9
    },
    {
        "timestamp": "2025-06-25 19:09:48",
        "count": 10
    },
    {
        "timestamp": "2025-06-25 19:10:18",
        "count": 11
    },
    {
        "timestamp": "2025-06-25 19:10:38",
        "count": 10
    },
    {
        "timestamp": "2025-06-25 19:10:48",
        "count": 11
    }
]